statuslight_client/__init__.py
statuslight_client/statuslight-client.py
statuslight_client-0.1.0.dist-info/WHEEL
statuslight_client-0.1.0.dist-info/METADATA
statuslight_client-0.1.0.dist-info/RECORD
