Metadata-Version: 2.1
Name: statuslight-client
Version: 0.1.0
Summary: 
Home-page: UNKNOWN
License: MIT
Author: Daniel Bengtsson
Author-email: daniel.f.bengtsson@gmail.com
Requires-Python: >=3.6,<4.0
Classifier: License :: OSI Approved :: MIT License
Classifier: Programming Language :: Python :: 3
Classifier: Programming Language :: Python :: 3.6
Classifier: Programming Language :: Python :: 3.7
Requires-Dist: pyserial (>=3.4,<4.0)
